{"directed": false, "multigraph": false, "graph": {}, "nodes": [{"centrality": 0.15789473684210525, "id": 0}, {"centrality": 0.10526315789473684, "id": 1}, {"centrality": 0.15789473684210525, "id": 2}, {"centrality": 0.10526315789473684, "id": 3}, {"centrality": 0.05263157894736842, "id": 4}, {"centrality": 0.10526315789473684, "id": 5}, {"centrality": 0.15789473684210525, "id": 6}, {"centrality": 0.10526315789473684, "id": 7}, {"centrality": 0.15789473684210525, "id": 8}, {"centrality": 0.2631578947368421, "id": 9}, {"centrality": 0.10526315789473684, "id": 10}, {"centrality": 0.10526315789473684, "id": 11}, {"centrality": 0.21052631578947367, "id": 12}, {"centrality": 0.15789473684210525, "id": 13}, {"centrality": 0.10526315789473684, "id": 14}, {"centrality": 0.10526315789473684, "id": 15}, {"centrality": 0.10526315789473684, "id": 16}, {"centrality": 0.0, "id": 17}, {"centrality": 0.2631578947368421, "id": 18}, {"centrality": 0.10526315789473684, "id": 19}], "links": [{"source": 0, "target": 16}, {"source": 0, "target": 6}, {"source": 0, "target": 5}, {"source": 1, "target": 9}, {"source": 1, "target": 19}, {"source": 2, "target": 6}, {"source": 2, "target": 13}, {"source": 2, "target": 15}, {"source": 3, "target": 9}, {"source": 3, "target": 19}, {"source": 4, "target": 18}, {"source": 5, "target": 18}, {"source": 6, "target": 11}, {"source": 7, "target": 12}, {"source": 7, "target": 15}, {"source": 8, "target": 9}, {"source": 8, "target": 13}, {"source": 8, "target": 14}, {"source": 9, "target": 12}, {"source": 9, "target": 18}, {"source": 10, "target": 16}, {"source": 10, "target": 11}, {"source": 12, "target": 13}, {"source": 12, "target": 18}, {"source": 14, "target": 18}]}